[
  {
    "site": "manualeconomy",
    "pageType": "home",
    "requestedUrl": "https://manualeconomy.kz/",
    "finalUrl": "https://manualeconomy.kz/",
    "status": 200,
    "title": "Ручная экономика | Независимый взгляд на экономику Казахстана. Аналитика банковского сектора, фондовые рынки, новости крупного бизнеса и эксклюзивные истории о ключевых игроках рынка.",
    "description": "Независимый взгляд на экономику Казахстана. Аналитика банковского сектора, фондовые рынки, новости крупного бизнеса и эксклюзивные истории о ключевых игроках рынка.",
    "generator": null,
    "screenshot": "/portfolio/work/manualeconomy/home-1920x1080.jpg",
    "viewport": "1920x1080",
    "capturedAt": "2026-07-14T12:53:41.586Z",
    "durationMs": 35566
  },
  {
    "site": "manualeconomy",
    "pageType": "category-markets",
    "requestedUrl": "https://manualeconomy.kz/category/rynky/",
    "finalUrl": "https://manualeconomy.kz/category/rynky/",
    "status": 200,
    "title": "рынки | Ручная экономика",
    "description": null,
    "generator": null,
    "screenshot": "/portfolio/work/manualeconomy/category-markets-1920x1080.jpg",
    "viewport": "1920x1080",
    "capturedAt": "2026-07-14T12:54:46.500Z",
    "durationMs": 64858
  },
  {
    "site": "manualeconomy",
    "pageType": "article",
    "requestedUrl": "https://manualeconomy.kz/kak-investory-reagirovali-na-pokupku-fortebank-bulata-utemuratova-nebolshogo-home-credit-bank/",
    "finalUrl": "https://manualeconomy.kz/kak-investory-reagirovali-na-pokupku-fortebank-bulata-utemuratova-nebolshogo-home-credit-bank/",
    "status": 200,
    "title": "Как инвесторы реагировали на покупку ForteBank Булата Утемуратова небольшого Home Credit Bank | Ручная экономика",
    "description": "Бумаги банка перед сделкой стоили 7,9 тенге, а сегодня торгуются по 10,4 тенге.",
    "generator": null,
    "screenshot": "/portfolio/work/manualeconomy/article-1920x1080.jpg",
    "viewport": "1920x1080",
    "capturedAt": "2026-07-14T12:55:21.205Z",
    "durationMs": 34648
  },
  {
    "site": "zhasalash",
    "pageType": "home",
    "requestedUrl": "https://zhasalash.kz/",
    "finalUrl": "https://zhasalash.kz/",
    "status": 200,
    "title": "Jasalash",
    "description": null,
    "generator": null,
    "screenshot": "/portfolio/work/zhasalash/home-1920x1080.jpg",
    "viewport": "1920x1080",
    "capturedAt": "2026-07-14T12:58:17.047Z",
    "durationMs": 65354
  },
  {
    "site": "zhasalash",
    "pageType": "category-analysis",
    "requestedUrl": "https://zhasalash.kz/categories/saraptama/",
    "finalUrl": "https://zhasalash.kz/categories/saraptama/",
    "status": 200,
    "title": "Jasalash | Сараптама",
    "description": null,
    "generator": null,
    "screenshot": "/portfolio/work/zhasalash/category-analysis-1920x1080.jpg",
    "viewport": "1920x1080",
    "capturedAt": "2026-07-14T12:59:22.017Z",
    "durationMs": 64904
  },
  {
    "site": "zhasalash",
    "pageType": "article",
    "requestedUrl": "https://zhasalash.kz/news/ulttik-kompaniya-basshilari-siyakiga-kashan-toyadi-32a0b5/",
    "finalUrl": "https://zhasalash.kz/news/ulttik-kompaniya-basshilari-siyakiga-kashan-toyadi-32a0b5/",
    "status": 200,
    "title": "Ұлттық компания басшылары сыйақыға қашан тояды?",
    "description": null,
    "generator": null,
    "screenshot": "/portfolio/work/zhasalash/article-1920x1080.jpg",
    "viewport": "1920x1080",
    "capturedAt": "2026-07-14T13:00:26.961Z",
    "durationMs": 64873
  },
  {
    "site": "nofake",
    "pageType": "home",
    "requestedUrl": "https://nofake.kz/",
    "finalUrl": "https://nofake.kz/",
    "status": 200,
    "title": "NoFake - Портал по борьбе с фейками. Проверенные факты, аналитика, расследования, статьи о критическом мышлении и цифровой безопасности.",
    "description": null,
    "generator": null,
    "screenshot": "/portfolio/work/nofake/home-1920x1080.jpg",
    "viewport": "1920x1080",
    "capturedAt": "2026-07-14T13:01:01.970Z",
    "durationMs": 34944
  },
  {
    "site": "nofake",
    "pageType": "category-analytics",
    "requestedUrl": "https://nofake.kz/category/analytics/",
    "finalUrl": "https://nofake.kz/category/analytics/",
    "status": 200,
    "title": "Архивы Аналитика - NoFake",
    "description": null,
    "generator": null,
    "screenshot": "/portfolio/work/nofake/category-analytics-1920x1080.jpg",
    "viewport": "1920x1080",
    "capturedAt": "2026-07-14T13:01:38.371Z",
    "durationMs": 36339
  },
  {
    "site": "nofake",
    "pageType": "article",
    "requestedUrl": "https://nofake.kz/sozdali-dipfejk-za-minutu-pochemu-eto-dolzhno-bespokoit-kazahstan/",
    "finalUrl": "https://nofake.kz/sozdali-dipfejk-za-minutu-pochemu-eto-dolzhno-bespokoit-kazahstan/",
    "status": 200,
    "title": "Создали дипфейк за минуту: почему это должно беспокоить Казахстан - NoFake",
    "description": null,
    "generator": null,
    "screenshot": "/portfolio/work/nofake/article-1920x1080.jpg",
    "viewport": "1920x1080",
    "capturedAt": "2026-07-14T13:02:16.642Z",
    "durationMs": 38183
  },
  {
    "site": "nationalbusiness",
    "pageType": "home",
    "requestedUrl": "https://nationalbusiness.kz/",
    "finalUrl": "https://nationalbusiness.kz/",
    "status": 200,
    "title": "nationalbusiness.kz ᐈ Бизнес аналитика в Казахстане",
    "description": "Национальный бизнес-портал о Казахстане. Актуальная бизнес-аналитика, экономика, финансы, интервью с экспертами и обзоры ключевых отраслей региона на nationalbusiness.kz.",
    "generator": null,
    "screenshot": "/portfolio/work/nationalbusiness/home-1920x1080.jpg",
    "viewport": "1920x1080",
    "capturedAt": "2026-07-14T13:02:53.084Z",
    "durationMs": 36275
  },
  {
    "site": "nationalbusiness",
    "pageType": "category-economy",
    "requestedUrl": "https://nationalbusiness.kz/category/ekonomika/",
    "finalUrl": "https://nationalbusiness.kz/category/ekonomika/",
    "status": 200,
    "title": "Экономика",
    "description": "Новости и аналитика мировой и казахстанской экономики. Рынки, инвестиции, бизнес-тренды и ключевые события, влияющие на развитие.",
    "generator": null,
    "screenshot": "/portfolio/work/nationalbusiness/category-economy-1920x1080.jpg",
    "viewport": "1920x1080",
    "capturedAt": "2026-07-14T13:03:28.089Z",
    "durationMs": 34930
  },
  {
    "site": "nationalbusiness",
    "pageType": "article",
    "requestedUrl": "https://nationalbusiness.kz/news/ekonomist-obyasnil-pochemu-razdel-erg-vigoden-kazahstanu-f27200/",
    "finalUrl": "https://nationalbusiness.kz/news/ekonomist-obyasnil-pochemu-razdel-erg-vigoden-kazahstanu-f27200/",
    "status": 200,
    "title": "Экономист объяснил, почему раздел ERG выгоден Казахстану",
    "description": "Это поможет быстрее выплатить миллиардные долги российским банкам",
    "generator": null,
    "screenshot": "/portfolio/work/nationalbusiness/article-1920x1080.jpg",
    "viewport": "1920x1080",
    "capturedAt": "2026-07-14T13:04:02.944Z",
    "durationMs": 34784
  },
  {
    "site": "modernization",
    "pageType": "home",
    "requestedUrl": "https://modernization.kz/ru/",
    "finalUrl": "https://modernization.kz/ru/",
    "status": 200,
    "title": "МЭКС - Национальный проект Казахстана по модернизации энергетики и ЖКХ | МЭКС",
    "description": "МЭКС – Узнайте о национальном проекте Казахстана по модернизации энергетики и ЖКХ: планы, новости, интерактивная карта и FAQ для устойчивого развития инфраструктуры.",
    "generator": null,
    "screenshot": "/portfolio/work/modernization/home-1920x1080.jpg",
    "viewport": "1920x1080",
    "capturedAt": "2026-07-14T13:06:54.352Z",
    "durationMs": 39949
  },
  {
    "site": "modernization",
    "pageType": "projects",
    "requestedUrl": "https://modernization.kz/ru/projects",
    "finalUrl": "https://modernization.kz/ru/projects",
    "status": 200,
    "title": "Проекты",
    "description": "",
    "generator": null,
    "screenshot": "/portfolio/work/modernization/projects-1920x1080.jpg",
    "viewport": "1920x1080",
    "capturedAt": "2026-07-14T13:07:30.290Z",
    "durationMs": 35849
  },
  {
    "site": "modernization",
    "pageType": "article",
    "requestedUrl": "https://modernization.kz/ru/news/v-aksu-obnovili-teplomagistral-stabilnoe-teplo-poluchat-jiteli-shesti",
    "finalUrl": "https://modernization.kz/ru/news/v-aksu-obnovili-teplomagistral-stabilnoe-teplo-poluchat-jiteli-shesti",
    "status": 200,
    "title": "В Аксу обновили тепломагистраль: стабильное тепло получат жители шести микрорайонов",
    "description": "В городе Аксу Павлодарской области завершили реконструкцию тепломагистрали по улице Астана. Именно от этого участка зависит подача тепла в дома жителей шести...",
    "generator": null,
    "screenshot": "/portfolio/work/modernization/article-1920x1080.jpg",
    "viewport": "1920x1080",
    "capturedAt": "2026-07-14T13:08:06.133Z",
    "durationMs": 35774
  }
]
